{
  "main": {
    "id": "b8807beedd78032a",
    "type": "split",
    "children": [
      {
        "id": "e77832185e87198c",
        "type": "tabs",
        "children": [
          {
            "id": "8f998ec62862901e",
            "type": "leaf",
            "state": {
              "type": "image",
              "state": {
                "file": "images/Pasted image 20251210212252.png"
              },
              "icon": "lucide-image",
              "title": "Pasted image 20251210212252"
            }
          },
          {
            "id": "820e55fd93739629",
            "type": "leaf",
            "state": {
              "type": "markdown",
              "state": {
                "file": "Junior Cybersecurity Analyst/Network/Wireless networks.md",
                "mode": "source",
                "source": false
              },
              "icon": "lucide-file",
              "title": "Wireless networks"
            }
          }
        ],
        "currentTab": 1
      }
    ],
    "direction": "vertical"
  },
  "left": {
    "id": "8947e7d9dcd929d7",
    "type": "split",
    "children": [
      {
        "id": "6a6bf05e5c784059",
        "type": "tabs",
        "children": [
          {
            "id": "ca5dc8d18ec2004e",
            "type": "leaf",
            "state": {
              "type": "file-explorer",
              "state": {
                "sortOrder": "alphabetical",
                "autoReveal": false
              },
              "icon": "lucide-folder-closed",
              "title": "Files"
            }
          },
          {
            "id": "f34199b1e1094475",
            "type": "leaf",
            "state": {
              "type": "search",
              "state": {
                "query": "",
                "matchingCase": false,
                "explainSearch": false,
                "collapseAll": false,
                "extraContext": false,
                "sortOrder": "alphabetical"
              },
              "icon": "lucide-search",
              "title": "Search"
            }
          },
          {
            "id": "90a6bfd7271dcf63",
            "type": "leaf",
            "state": {
              "type": "bookmarks",
              "state": {},
              "icon": "lucide-bookmark",
              "title": "Bookmarks"
            }
          }
        ]
      }
    ],
    "direction": "horizontal",
    "width": 300
  },
  "right": {
    "id": "43423b243cc6db98",
    "type": "split",
    "children": [
      {
        "id": "0c4cbff87f665246",
        "type": "tabs",
        "children": [
          {
            "id": "d10bbe8e4e5ffcea",
            "type": "leaf",
            "state": {
              "type": "backlink",
              "state": {
                "file": "Welcome.md",
                "collapseAll": false,
                "extraContext": false,
                "sortOrder": "alphabetical",
                "showSearch": false,
                "searchQuery": "",
                "backlinkCollapsed": false,
                "unlinkedCollapsed": true
              },
              "icon": "links-coming-in",
              "title": "Backlinks for Welcome"
            }
          },
          {
            "id": "bdacbb0fe558b746",
            "type": "leaf",
            "state": {
              "type": "outgoing-link",
              "state": {
                "file": "Welcome.md",
                "linksCollapsed": false,
                "unlinkedCollapsed": true
              },
              "icon": "links-going-out",
              "title": "Outgoing links from Welcome"
            }
          },
          {
            "id": "3adf56edeced9f0c",
            "type": "leaf",
            "state": {
              "type": "tag",
              "state": {
                "sortOrder": "frequency",
                "useHierarchy": true,
                "showSearch": false,
                "searchQuery": ""
              },
              "icon": "lucide-tags",
              "title": "Tags"
            }
          },
          {
            "id": "23fd3c937af00714",
            "type": "leaf",
            "state": {
              "type": "outline",
              "state": {
                "file": "Welcome.md",
                "followCursor": false,
                "showSearch": false,
                "searchQuery": ""
              },
              "icon": "lucide-list",
              "title": "Outline of Welcome"
            }
          },
          {
            "id": "94e045c837942777",
            "type": "leaf",
            "state": {
              "type": "git-view",
              "state": {},
              "icon": "git-pull-request",
              "title": "Source Control"
            }
          }
        ],
        "currentTab": 4
      }
    ],
    "direction": "horizontal",
    "width": 300
  },
  "left-ribbon": {
    "hiddenItems": {
      "bases:Create new base": false,
      "obsidian-git:Open Git source control": false,
      "switcher:Open quick switcher": false,
      "graph:Open graph view": false,
      "canvas:Create new canvas": false,
      "daily-notes:Open today's daily note": false,
      "templates:Insert template": false,
      "command-palette:Open command palette": false
    }
  },
  "active": "820e55fd93739629",
  "lastOpenFiles": [
    "Pasted image 20251216185309.png",
    "Junior Cybersecurity Analyst/Network/Protocols & Terminology.md",
    "Junior Cybersecurity Analyst/Network/Wireless networks.md",
    "Junior Cybersecurity Analyst/Network/Proxies.md",
    "Junior Cybersecurity Analyst/Network/Networking tools.md",
    "Junior Cybersecurity Analyst/Network/Adressing.md",
    "Junior Cybersecurity Analyst/Network/Networking structure.md",
    "Junior Cybersecurity Analyst/Network/Networking workflow.md",
    "images/Pasted image 20251210210340.png",
    "images/Pasted image 20251210212252.png",
    "Junior Cybersecurity Analyst/Introduction to Information Security/Threats.md",
    "images/Pasted image 20251210141546.png",
    "conflict-files-obsidian-git.md",
    "Junior Cybersecurity Analyst/Introduction to Information Security/Network",
    "images/Pasted image 20251210142025.png",
    "images/Pasted image 20251210141859.png",
    "images/Pasted image 20251210141655.png",
    "images/Pasted image 20251210141006.png",
    "images/Pasted image 20251210140759.png",
    "images/Pasted image 20251210140542.png",
    "images/Pasted image 20251210140503.png",
    "Junior Cybersecurity Analyst/Network",
    "Junior Cybersecurity Analyst/Introduction to Information Security/Domains/Physical Security.md",
    "Junior Cybersecurity Analyst/Introduction to Information Security/Domains/Operational Security.md",
    "Junior Cybersecurity Analyst/Introduction to Information Security/Domains/Network Security.md",
    "Junior Cybersecurity Analyst/Introduction to Information Security/Domains/Mobile Security.md",
    "Junior Cybersecurity Analyst/Introduction to Information Security/Domains/IOT security.md",
    "Junior Cybersecurity Analyst/Introduction to Information Security/Domains/Disaster Recovery and Business Continuity.md",
    "Junior Cybersecurity Analyst/Introduction to Information Security/Domains/Cloud Security.md",
    "Junior Cybersecurity Analyst/Introduction to Information Security/Domains/Application Security.md",
    "Junior Cybersecurity Analyst/Introduction to Information Security/Threats",
    "Junior Cybersecurity Analyst/Introduction to Information Security/Introduction/Principles of Information Security.md",
    "Junior Cybersecurity Analyst/Introduction to Information Security/Introduction/Structure of InfoSec.md",
    "Junior Cybersecurity Analyst/Introduction to Information Security/Domains",
    "Junior Cybersecurity Analyst/Introduction to Information Security/Introduction",
    "images",
    "Junior Cybersecurity Analyst/Introduction to Information Security",
    "Junior Cybersecurity Analyst",
    "Welcome.md"
  ]
}